physicsx/component_host/.ruff_cache/.gitignore
physicsx/component_host/.ruff_cache/0.14.7/11553222466149081417
physicsx/component_host/.ruff_cache/CACHEDIR.TAG
physicsx/component_host/__init__.py
physicsx/component_host/__main__.py
physicsx/component_host/_component.py
physicsx/component_host/_entrypoint.py
physicsx/component_host/_execute.py
physicsx/component_host/py.typed
physicsx_component_host-0.1.0.dist-info/WHEEL
physicsx_component_host-0.1.0.dist-info/entry_points.txt
physicsx_component_host-0.1.0.dist-info/METADATA
physicsx_component_host-0.1.0.dist-info/RECORD
