Metadata-Version: 2.3
Name: physicsx-component-host
Version: 0.1.0
Summary: PXC-002 Component Host implementation
Requires-Dist: pydantic~=2.7
Requires-Dist: physicsx-component-protocol
Requires-Python: >=3.10, <3.15
